{
    "Hide": 0b,
    "Fov": 70.0f,
    "Morphs": [
        {
            "Expire": 60,
            "Ortho": 0b,
            "Morph": {
                "List": [
                    {
                        "Random": 0.0f,
                        "SetDuration": 0b,
                        "Morph": {
                            "Color": 16777215,
                            "Animation": {
                                "Interp": 21,
                                "Animates": 1b
                            },
                            "Texture": "b.a:1_HOTEL/sprites/ht_logo2.png",
                            "Name": "blockbuster.image"
                        },
                        "Duration": 10.0f,
                        "EndPoint": 0b
                    },
                    {
                        "Random": 0.0f,
                        "SetDuration": 0b,
                        "Morph": {
                            "Animation": {
                                "Interp": 21,
                                "Animates": 1b
                            },
                            "Texture": "b.a:1_HOTEL/sprites/ht_logo2.png",
                            "Name": "blockbuster.image"
                        },
                        "Duration": 40.0f,
                        "EndPoint": 0b
                    },
                    {
                        "Random": 0.0f,
                        "SetDuration": 0b,
                        "Morph": {
                            "Color": 16777215,
                            "Animation": {
                                "Interp": 21,
                                "Animates": 1b
                            },
                            "Texture": "b.a:1_HOTEL/sprites/ht_logo2.png",
                            "Name": "blockbuster.image"
                        },
                        "Duration": 10.0f,
                        "EndPoint": 0b
                    }
                ],
                "Name": "sequencer",
                "Offset": [
                    0.0f,
                    0.0f,
                    0.0f
                ]
            },
            "OrthoY": 0.0f,
            "Scale": [
                2.0f,
                2.0f,
                2.0f
            ],
            "OrthoX": 0.0f,
            "Translate": [
                0.0f,
                1.0f,
                0.0f
            ]
        },
        {
            "Expire": 55,
            "Ortho": 0b,
            "Morph": {
                "List": [
                    {
                        "Random": 0.0f,
                        "SetDuration": 0b,
                        "Morph": {
                            "Animation": {
                                "Interp": 21,
                                "Animates": 1b
                            },
                            "Skin": "b.a:empty/skins/texture.png",
                            "CustomPose": {
                                "Size": [
                                    1.0f,
                                    1.0f,
                                    1.0f
                                ],
                                "Poses": {
                                    "cube": {
                                        "S": [
                                            1.0f,
                                            0.0f,
                                            1.0f
                                        ]
                                    }
                                }
                            },
                            "BodyParts": [
                                {
                                    "Limb": "cube",
                                    "Morph": {
                                        "Label": "by [c[lNZ[fTEAM",
                                        "Name": "label"
                                    }
                                }
                            ],
                            "Settings": {
                                "Hands": 1b
                            },
                            "Name": "blockbuster.empty"
                        },
                        "Duration": 15.0f,
                        "EndPoint": 0b
                    },
                    {
                        "Random": 0.0f,
                        "SetDuration": 0b,
                        "Morph": {
                            "Animation": {
                                "Interp": 21,
                                "Animates": 1b,
                                "Duration": 5
                            },
                            "Skin": "b.a:empty/skins/texture.png",
                            "CustomPose": {
                                "Size": [
                                    1.0f,
                                    1.0f,
                                    1.0f
                                ],
                                "Poses": {
                                    "cube": {
                                    }
                                }
                            },
                            "BodyParts": [
                                {
                                    "Limb": "cube",
                                    "Morph": {
                                        "Label": "by [c[lNZ[fTEAM",
                                        "Name": "label"
                                    }
                                }
                            ],
                            "Settings": {
                                "Hands": 1b
                            },
                            "Name": "blockbuster.empty"
                        },
                        "Duration": 5.0f,
                        "EndPoint": 0b
                    },
                    {
                        "Random": 0.0f,
                        "SetDuration": 0b,
                        "Morph": {
                            "Animation": {
                                "Interp": 21,
                                "Animates": 1b
                            },
                            "Skin": "b.a:empty/skins/texture.png",
                            "CustomPose": {
                                "Size": [
                                    1.0f,
                                    1.0f,
                                    1.0f
                                ],
                                "Poses": {
                                    "cube": {
                                    }
                                }
                            },
                            "BodyParts": [
                                {
                                    "Limb": "cube",
                                    "Morph": {
                                        "Label": "by [c[lNZ[fTEAM",
                                        "Name": "label"
                                    }
                                }
                            ],
                            "Settings": {
                                "Hands": 1b
                            },
                            "Name": "blockbuster.empty"
                        },
                        "Duration": 30.0f,
                        "EndPoint": 0b
                    },
                    {
                        "Random": 0.0f,
                        "SetDuration": 0b,
                        "Morph": {
                            "Animation": {
                                "Interp": 21,
                                "Animates": 1b,
                                "Duration": 5
                            },
                            "Skin": "b.a:empty/skins/texture.png",
                            "CustomPose": {
                                "Size": [
                                    1.0f,
                                    1.0f,
                                    1.0f
                                ],
                                "Poses": {
                                    "cube": {
                                        "S": [
                                            1.0f,
                                            0.0f,
                                            1.0f
                                        ]
                                    }
                                }
                            },
                            "BodyParts": [
                                {
                                    "Limb": "cube",
                                    "Morph": {
                                        "Label": "by [c[lNZ[fTEAM",
                                        "Name": "label"
                                    }
                                }
                            ],
                            "Settings": {
                                "Hands": 1b
                            },
                            "Name": "blockbuster.empty"
                        },
                        "Duration": 5.0f,
                        "EndPoint": 0b
                    }
                ],
                "Name": "sequencer",
                "Offset": [
                    0.0f,
                    0.0f,
                    0.0f
                ]
            },
            "OrthoY": 0.0f,
            "Scale": [
                0.5f,
                0.5f,
                0.5f
            ],
            "OrthoX": 0.0f,
            "Translate": [
                0.22625f,
                0.72f,
                0.0f
            ]
        }
    ],
    "Global": 0b
}